module/SesamCli.py
module/__init__.py
module/module.py
module/utils.py
tests/__init__.py
tests/test_module.py
NonoSesam-1.0.dist-info/LICENSE
NonoSesam-1.0.dist-info/METADATA
NonoSesam-1.0.dist-info/WHEEL
NonoSesam-1.0.dist-info/top_level.txt
NonoSesam-1.0.dist-info/RECORD
