Metadata-Version: 2.1
Name: NonoSesam
Version: 1.0
Summary: A flexible secret management system
Home-page: https://github.com/lopezmartin/sesam
Author: Miguel Lopez
Author-email: miguel@lopezmartin.me
Classifier: Programming Language :: Python :: 3
Classifier: License :: OSI Approved :: MIT License
Classifier: Operating System :: OS Independent
Requires-Python: >=3.9
License-File: LICENSE
Requires-Dist: python-dotenv
Requires-Dist: cryptography
Requires-Dist: pytest
